{
	"id": "english-environment",
	"name": "Balance Flow - English",
	"values": [
		{
			"key": "base_url",
			"value": "http://localhost:8080",
			"type": "default",
			"enabled": true
		},
		{
			"key": "locale",
			"value": "en",
			"type": "default",
			"enabled": true
		},
		{
			"key": "access_token",
			"value": "",
			"type": "secret",
			"enabled": true
		},
		{
			"key": "user_id",
			"value": "",
			"type": "default",
			"enabled": true
		},
		{
			"key": "category_id",
			"value": "",
			"type": "default",
			"enabled": true
		}
	],
	"_postman_variable_scope": "environment"
}
